darth/__init__.py
darth/downloader.py
darth/obsclient.py
darth/process.py
darth/raster.py
darth/subscription.py
darth/transform.py
darth/vector.py
obs-src/__init__.py
obs-src/setup.py
obs-src/obs/__init__.py
obs-src/obs/auth.py
obs-src/obs/bucket.py
obs-src/obs/bulktasks.py
obs-src/obs/cache.py
obs-src/obs/client.py
obs-src/obs/const.py
obs-src/obs/convertor.py
obs-src/obs/extension.py
obs-src/obs/http2.py
obs-src/obs/ilog.py
obs-src/obs/loadtoken.py
obs-src/obs/locks.py
obs-src/obs/model.py
obs-src/obs/progress.py
obs-src/obs/searchmethod.py
obs-src/obs/transfer.py
obs-src/obs/util.py
d_arth-0.1.8.dist-info/LICENSE
d_arth-0.1.8.dist-info/METADATA
d_arth-0.1.8.dist-info/WHEEL
d_arth-0.1.8.dist-info/top_level.txt
d_arth-0.1.8.dist-info/RECORD
