Metadata-Version: 2.1
Name: d-arth
Version: 0.1.8
Summary: The Satellite Imagery DataSet Toolkit
Home-page: https://github.com/OOXXXXOO/DARTH
Author: Winshare Tom
Author-email: tanwenxuan@live.com
License: Apache License Version 2.0
Platform: UNKNOWN
Classifier: Programming Language :: Python :: 3.6
Classifier: License :: OSI Approved :: MIT License
Classifier: Operating System :: OS Independent
Requires-Python: >=3.6
License-File: LICENSE
Requires-Dist: certifi
Requires-Dist: decorating
Requires-Dist: esdk-obs-python
Requires-Dist: tqdm
Requires-Dist: olefile
Requires-Dist: python-slugify
Requires-Dist: text-unidecode
Requires-Dist: GDAL
Requires-Dist: numpy
Requires-Dist: Pillow
